iitb_oauth/__init__.py
iitb_oauth/backend.py
iitb_oauth/helpers.py
iitb_oauth/urls.py
iitb_oauth/views.py
iitb_oauth/migrations/__init__.py
iitb_oauth-1.2.dist-info/LICENSE
iitb_oauth-1.2.dist-info/METADATA
iitb_oauth-1.2.dist-info/WHEEL
iitb_oauth-1.2.dist-info/top_level.txt
iitb_oauth-1.2.dist-info/RECORD
