Metadata-Version: 2.1
Name: iitb-oauth
Version: 1.2
Summary: Django app for LDAP authentication using IIT Bombay gymkhana SSO.
Home-page: UNKNOWN
Author: Nautatava Navlakha
Author-email: nnautatva@gmail.com
License: UNKNOWN
Project-URL: Travis CI, https://travis-ci.org/github/nautatva/iitb_oauth/
Project-URL: Source code, https://github.com/nautatva/iitb_oauth/
Platform: UNKNOWN
Classifier: Intended Audience :: Developers
Classifier: Programming Language :: Python
Classifier: Programming Language :: Python :: 2.7
Classifier: Programming Language :: Python :: 3
Classifier: Programming Language :: Python :: 3.5
Classifier: Programming Language :: Python :: 3.6
Classifier: Programming Language :: Python :: 3.7
Classifier: Programming Language :: Python :: 3.8
Classifier: Environment :: Web Environment
Classifier: Framework :: Django
Classifier: Operating System :: OS Independent
Classifier: License :: OSI Approved :: MIT License
Classifier: Natural Language :: English
Classifier: Topic :: Internet :: WWW/HTTP :: Dynamic Content
Classifier: Topic :: Software Development
Classifier: Topic :: Software Development :: Libraries :: Application Frameworks
Classifier: Framework :: Django
Classifier: Framework :: Django :: 1.11
Classifier: Framework :: Django :: 2.0
Classifier: Framework :: Django :: 2.1
Classifier: Framework :: Django :: 2.2
Classifier: Framework :: Django :: 3.0
Requires-Python: >1.1.1
Requires-Dist: Django
Requires-Dist: requests
